django_twilio_access_token/__init__.py
django_twilio_access_token/urls.py
django_twilio_access_token/serializers/__init__.py
django_twilio_access_token/serializers/twilio_access_token_serializer.py
django_twilio_access_token/serializers/twilio_room_serializer.py
django_twilio_access_token/views/__init__.py
django_twilio_access_token/views/twilio_room_view.py
django_twilio_access_token/views/twilio_video_access_token_view.py
django_twilio_access_token-0.0.5.dist-info/METADATA
django_twilio_access_token-0.0.5.dist-info/WHEEL
django_twilio_access_token-0.0.5.dist-info/top_level.txt
django_twilio_access_token-0.0.5.dist-info/RECORD
