Metadata-Version: 2.1
Name: django-twilio-access-token
Version: 0.0.5
Summary: A Django app to generate Twilio access token for particular Twilio services.
Home-page: https://github.com/senseobservationsystems/django-twilio-access-token/
Author: Panji Y. Wiwaha
Author-email: panjiyudasetya@gmail.com
License: UNKNOWN
Keywords: django,twilio,access,token
Platform: UNKNOWN
Classifier: Environment :: Web Environment
Classifier: Framework :: Django
Classifier: Programming Language :: Python :: 3
Classifier: License :: OSI Approved :: MIT License
Classifier: Operating System :: OS Independent
Classifier: Programming Language :: Python
Classifier: Programming Language :: Python :: 2.7
Classifier: Programming Language :: Python :: 3.3
Classifier: Topic :: Software Development :: Libraries :: Python Modules
Classifier: Topic :: Utilities
Classifier: Topic :: Software Development :: Libraries :: Application Frameworks
Classifier: Topic :: Software Development :: Libraries :: Python Modules
Requires-Dist: django
Requires-Dist: djangorestframework
Requires-Dist: drf-rw-serializers
Requires-Dist: python-dateutil
Requires-Dist: twilio
